example.py
context_configuration/__init__.py
context_configuration/context_configuration.py
context_configuration/default_property_source_loader.py
context_configuration/converter/__init__.py
context_configuration/converter/dataclass_converter.py
context_configuration/converter/default_converter.py
context_configuration/converter/iso_format_datetime_converter.py
context_configuration/property_source/__init__.py
context_configuration/property_source/abstract_property_source.py
context_configuration/property_source/cli_property_source.py
context_configuration/property_source/dictionary_property_source.py
context_configuration/property_source/env_vars_property_source.py
context_configuration/property_source/pyyaml_property_source.py
context_configuration/protocol/__init__.py
context_configuration/protocol/converter.py
context_configuration/protocol/property_source.py
context_configuration-0.0.1.dist-info/licenses/LICENSE
context_configuration-0.0.1.dist-info/METADATA
context_configuration-0.0.1.dist-info/WHEEL
context_configuration-0.0.1.dist-info/top_level.txt
context_configuration-0.0.1.dist-info/RECORD
